{"type": "FeatureCollection", "features": [{"type": "Feature", "properties": {"Diorama name": "American bison", "Continent": "NorthAmerica", "Scientific name": "Bos bison"}, "geometry": {"type": "Point", "coordinates": [-114.23338463785969, 34.276114719086706]}}]}
