{"type": "FeatureCollection", "features": [{"type": "Feature", "properties": {"Diorama name": "Beaver", "Continent": "NorthAmerica", "Scientific name": "Castor canadensis"}, "geometry": {"type": "Point", "coordinates": [-110.259013, 43.519211]}}]}