{"type": "FeatureCollection", "features": [{"type": "Feature", "properties": {"Diorama name": "Tule elk", "Continent": "NorthAmerica", "Scientific name": "Cervus elephas nannodes"}, "geometry": {"type": "Point", "coordinates": [-119.954696, 35.177921]}}]}