{"type": "FeatureCollection", "features": [{"type": "Feature", "properties": {"Diorama name": "Fisher", "Continent": "NorthAmerica", "Scientific name": "Pekania pennanti"}, "geometry": {"type": "Point", "coordinates": [-118.625774, 37.171232]}}]}