{"type": "FeatureCollection", "features": [{"type": "Feature", "properties": {"Diorama name": "Caribou", "Continent": "NorthAmerica", "Scientific name": "Rangifer tarandus"}, "geometry": {"type": "Point", "coordinates": [-145.196067, 66.738533]}}]}